githubapi2/__init__.py
githubapi2/__main__.py
githubapi2/githubuser.py
githubapi2/version.py
githubapi2-0.3.0.dist-info/LICENSE
githubapi2-0.3.0.dist-info/METADATA
githubapi2-0.3.0.dist-info/WHEEL
githubapi2-0.3.0.dist-info/entry_points.txt
githubapi2-0.3.0.dist-info/top_level.txt
githubapi2-0.3.0.dist-info/RECORD
